explicit/py.typed
explicit/unit_of_work.py
explicit/adapters/__init__.py
explicit/adapters/db.py
explicit/adapters/fs.py
explicit/adapters/messaging.py
explicit/contrib/__init__.py
explicit/contrib/domain/__init__.py
explicit/contrib/domain/model/__init__.py
explicit/contrib/domain/model/fields.py
explicit/contrib/messagebus/__init__.py
explicit/contrib/messagebus/event_registry.py
explicit/domain/__init__.py
explicit/domain/factories.py
explicit/domain/fields.py
explicit/domain/model.py
explicit/domain/types.py
explicit/domain/validation/__init__.py
explicit/domain/validation/exceptions.py
explicit/messagebus/__init__.py
explicit/messagebus/commands.py
explicit/messagebus/dependency_injection.py
explicit/messagebus/events.py
explicit/messagebus/exceptions.py
explicit/messagebus/messagebus.py
explicit/messagebus/queries.py
explicit_python-2.3.1.dist-info/METADATA
explicit_python-2.3.1.dist-info/WHEEL
explicit_python-2.3.1.dist-info/dependency_links.txt
explicit_python-2.3.1.dist-info/top_level.txt
explicit_python-2.3.1.dist-info/RECORD
